tad/__init__.py
tad/anomaly_detect_ts.py
tad/anomaly_detect_vec.py
tad/dynamic_cusum.py
tad/settings.py
tad-0.0.6.dist-info/LICENSE
tad-0.0.6.dist-info/METADATA
tad-0.0.6.dist-info/WHEEL
tad-0.0.6.dist-info/top_level.txt
tad-0.0.6.dist-info/RECORD
