Metadata-Version: 2.1
Name: tad
Version: 0.0.6
Summary: Twitter's Anomaly Detection Implementation in Python
Home-page: https://github.com/Marcnuth/AnomalyDetection
Author: Marcnuth
Author-email: hxianxian@gmail.com
License: Apache License 2.0
Platform: UNKNOWN
Classifier: Topic :: Scientific/Engineering :: Artificial Intelligence
Classifier: Topic :: Software Development :: Libraries
Classifier: Programming Language :: Python :: 3
